artist/__init__.py
artist/colormap.py
artist/multi_plot.py
artist/plot.py
artist/recursive_smooth.py
artist/simple_smooth.py
artist/utils.py
artist/templates/document.tex
artist/templates/multi_plot.tex
artist/templates/plot.tex
artist/templates/polar_plot.tex
artist/templates/subplot.tex
artist-0.17.0.dist-info/DESCRIPTION.rst
artist-0.17.0.dist-info/METADATA
artist-0.17.0.dist-info/RECORD
artist-0.17.0.dist-info/WHEEL
artist-0.17.0.dist-info/metadata.json
artist-0.17.0.dist-info/top_level.txt
