Metadata-Version: 2.0
Name: artist
Version: 0.17.0
Summary: A plotting library for Python with LaTeX output
Home-page: http://github.com/davidfokkema/artist/
Author: David Fokkema
Author-email: davidfokkema@icloud.com
License: GPLv3
Keywords: plots,plotting,data visualization
Platform: UNKNOWN
Classifier: Intended Audience :: Science/Research
Classifier: Intended Audience :: Education
Classifier: Operating System :: OS Independent
Classifier: Programming Language :: Python
Classifier: Programming Language :: Python :: 2.7
Classifier: Programming Language :: Python :: 3.4
Classifier: Topic :: Scientific/Engineering :: Visualization
Classifier: Topic :: Education
Classifier: Topic :: Text Processing :: Markup :: LaTeX
Classifier: License :: OSI Approved :: GNU General Public License v3 (GPLv3)
Requires-Dist: Pillow
Requires-Dist: jinja2
Requires-Dist: numpy
